ubears/__init__.py
ubears/data/govern_region/govern_region_level3.csv
ubears/data/govern_region/govern_region_level4.csv
ubears/data/userdict/jieba_dict_small.txt
ubears/flagbear/__init__.py
ubears/flagbear/const/__init__.py
ubears/flagbear/const/callables.py
ubears/flagbear/const/patterns.py
ubears/flagbear/const/prods.py
ubears/flagbear/const/tokens.py
ubears/flagbear/llp/__init__.py
ubears/flagbear/llp/autom.py
ubears/flagbear/llp/graph.py
ubears/flagbear/llp/lex.py
ubears/flagbear/llp/parser.py
ubears/flagbear/llp/syntax.py
ubears/flagbear/slp/__init__.py
ubears/flagbear/slp/db.py
ubears/flagbear/slp/finer.py
ubears/flagbear/slp/pdsl.py
ubears/flagbear/str2/__init__.py
ubears/flagbear/str2/dtyper.py
ubears/flagbear/str2/dups.py
ubears/flagbear/str2/fliper.py
ubears/flagbear/tree/__init__.py
ubears/flagbear/tree/tree.py
ubears/modsbear/__init__.py
ubears/modsbear/dflater/__init__.py
ubears/modsbear/dflater/ex2df.py
ubears/modsbear/dflater/ex4df.py
ubears/modsbear/dflater/exoptim.py
ubears/modsbear/dflater/sklwrap.py
ubears/modsbear/docer/__init__.py
ubears/modsbear/docer/pdframe.py
ubears/modsbear/locale/__init__.py
ubears/modsbear/locale/calender.py
ubears/modsbear/locale/geoenc.py
ubears/modsbear/locale/govreg.py
ubears/modsbear/locale/pronoun.py
ubears/modsbear/spanner/__init__.py
ubears/modsbear/spanner/dflog.py
ubears/modsbear/spanner/manidf.py
ubears/modsbear/stats/__init__.py
ubears/modsbear/stats/ahp.py
ubears/modsbear/stats/skltree.py
ubears/ringbear/__init__.py
ubears/ringbear/freqs.py
ubears/ringbear/metrics.py
ubears/ringbear/numeric.py
ubears/ringbear/sortable.py
ubears/ringbear/talib/__init__.py
ubears/ringbear/talib/momentum.py
ubears/ringbear/talib/overlap.py
ubears/ringbear/talib/ptnrecog.py
ubears/ringbear/timser/__init__.py
ubears/ringbear/timser/ovdd.py
ubears/suitbear/__init__.py
ubears/suitbear/deco.py
ubears/suitbear/autofin/__init__.py
ubears/suitbear/autofin/confagg.py
ubears/suitbear/autofin/confflat.py
ubears-0.2.4.dist-info/METADATA
ubears-0.2.4.dist-info/WHEEL
ubears-0.2.4.dist-info/top_level.txt
ubears-0.2.4.dist-info/RECORD
